{
    "title": "Some form",
    "type": "object",
    "properties": {
      "firstName": {
        "type": "string",
        "title": "First name"
      },
      "lastName": {
        "type": "string",
        "title": "Last name"
      }
    },
    "oneOf": [
      {
        "properties": {
          "homePhone": {
            "type": "number",
            "title": "Home phone"
          }
        },
        "required": [
          "homePhone"
        ]
      },
      {
        "properties": {
          "mobilePhone": {
            "type": "number",
            "title": "Mobile phone"
          }
        },
        "required": [
          "mobilePhone"
        ]
      }
    ]
  }